utils/common.py
utils/logger.py
utils/sepa.py
csv2sepa-1.2.4.dist-info/LICENSE
csv2sepa-1.2.4.dist-info/METADATA
csv2sepa-1.2.4.dist-info/WHEEL
csv2sepa-1.2.4.dist-info/top_level.txt
csv2sepa-1.2.4.dist-info/RECORD
