Metadata-Version: 2.2
Name: csv2sepa
Version: 1.2.4
Summary: CSV to SEPA Convertor
Author-email: Philippe-Alexandre Pierre <pap@httpap.dev>
Project-URL: homepage, https://gitlab.com/httpap/csv2sepa
Keywords: banking,batch,credit,csv,debit,excel,iso20022,sepa,xml,xsd
Classifier: Development Status :: 4 - Beta
Classifier: Intended Audience :: Developers
Classifier: Intended Audience :: Other Audience
Classifier: License :: OSI Approved :: MIT License
Classifier: Programming Language :: Python :: 3.9
Classifier: Programming Language :: Python :: 3.10
License-File: LICENSE
Requires-Dist: argparse
Requires-Dist: colorama
Requires-Dist: inquirer
Requires-Dist: logging
Requires-Dist: sepapy
